slurmrestapi/__init__.py
slurmrestapi/api_client.py
slurmrestapi/api_response.py
slurmrestapi/configuration.py
slurmrestapi/exceptions.py
slurmrestapi/py.typed
slurmrestapi/rest.py
slurmrestapi/api/__init__.py
slurmrestapi/api/slurm_api.py
slurmrestapi/api/slurmdb_api.py
slurmrestapi/models/__init__.py
slurmrestapi/models/dbv0039_account_info.py
slurmrestapi/models/dbv0039_associations_info.py
slurmrestapi/models/dbv0039_clusters_info.py
slurmrestapi/models/dbv0039_config_info.py
slurmrestapi/models/dbv0039_diag.py
slurmrestapi/models/dbv0039_error.py
slurmrestapi/models/dbv0039_job_info.py
slurmrestapi/models/dbv0039_meta.py
slurmrestapi/models/dbv0039_meta_plugin.py
slurmrestapi/models/dbv0039_meta_slurm.py
slurmrestapi/models/dbv0039_meta_slurm_version.py
slurmrestapi/models/dbv0039_qos_info.py
slurmrestapi/models/dbv0039_response_associations_delete.py
slurmrestapi/models/dbv0039_set_config.py
slurmrestapi/models/dbv0039_tres_info.py
slurmrestapi/models/dbv0039_tres_update.py
slurmrestapi/models/dbv0039_update_qos.py
slurmrestapi/models/dbv0039_update_users.py
slurmrestapi/models/dbv0039_user_info.py
slurmrestapi/models/dbv0039_warning.py
slurmrestapi/models/dbv0039_wckey_info.py
slurmrestapi/models/status.py
slurmrestapi/models/v0039_account.py
slurmrestapi/models/v0039_accounting.py
slurmrestapi/models/v0039_accounting_allocated.py
slurmrestapi/models/v0039_acct_gather_energy.py
slurmrestapi/models/v0039_assoc.py
slurmrestapi/models/v0039_assoc_default.py
slurmrestapi/models/v0039_assoc_max.py
slurmrestapi/models/v0039_assoc_max_jobs.py
slurmrestapi/models/v0039_assoc_max_jobs_per.py
slurmrestapi/models/v0039_assoc_max_per.py
slurmrestapi/models/v0039_assoc_max_per_account.py
slurmrestapi/models/v0039_assoc_max_tres.py
slurmrestapi/models/v0039_assoc_max_tres_group.py
slurmrestapi/models/v0039_assoc_max_tres_minutes.py
slurmrestapi/models/v0039_assoc_max_tres_minutes_per.py
slurmrestapi/models/v0039_assoc_max_tres_per.py
slurmrestapi/models/v0039_assoc_min.py
slurmrestapi-24.5.5.dist-info/METADATA
slurmrestapi-24.5.5.dist-info/WHEEL
slurmrestapi-24.5.5.dist-info/top_level.txt
slurmrestapi-24.5.5.dist-info/RECORD
