Metadata-Version: 2.1
Name: slurmrestapi
Version: 24.5.5
Summary: Slurm REST API
Home-page: 
Author: SchedMD LLC
Author-email: sales@schedmd.com
License: Apache 2.0
Keywords: OpenAPI,OpenAPI-Generator,Slurm REST API
Requires-Dist: urllib3<3.0.0,>=1.25.3
Requires-Dist: python-dateutil>=2.8.2
Requires-Dist: pydantic>=2
Requires-Dist: typing-extensions>=4.7.1
